RW/__init__.py
RW/Azure/__init__.py
RW/Azure/azure_alert_parser.py
RW/Dynatrace/__init__.py
RW/Dynatrace/dynatrace_parser.py
RW/GitHub/__init__.py
RW/GitHub/github_issues.py
RW/PagerDuty/__init__.py
RW/PagerDuty/pagerduty.py
RW/RunSession/__init__.py
RW/RunSession/runsession_utils.py
RW/Slack/__init__.py
RW/Slack/slack.py
RW/Workspace/__init__.py
RW/Workspace/workspace_utils.py
rw_workspace_utils-2025.11.3.1.dist-info/licenses/LICENSE
rw_workspace_utils-2025.11.3.1.dist-info/METADATA
rw_workspace_utils-2025.11.3.1.dist-info/WHEEL
rw_workspace_utils-2025.11.3.1.dist-info/top_level.txt
rw_workspace_utils-2025.11.3.1.dist-info/RECORD
