Metadata-Version: 2.4
Name: rw-workspace-utils
Version: 2025.11.3.1
Summary: RunWhen workspace utilities
Author-email: RunWhen <info@runwhen.com>
License: Apache License 2.0
Project-URL: homepage, https://github.com/runwhen-contrib/rw-workspace-utils
Classifier: Programming Language :: Python :: 3
Classifier: License :: OSI Approved :: Apache Software License
License-File: LICENSE
Requires-Dist: robotframework>=4.1.2
Requires-Dist: jmespath>=1.0.1
Requires-Dist: python-dateutil>=2.8.2
Requires-Dist: requests>=2.31.0
Requires-Dist: pyyaml
Requires-Dist: docker
Requires-Dist: azure-containerregistry
Requires-Dist: azure-identity
Requires-Dist: rw-cli-keywords>=0.0.23
Dynamic: license-file
